pephubclient/__init__.py
pephubclient/__main__.py
pephubclient/cli.py
pephubclient/constants.py
pephubclient/exceptions.py
pephubclient/files_manager.py
pephubclient/helpers.py
pephubclient/models.py
pephubclient/pephubclient.py
pephubclient/modules/__init__.py
pephubclient/modules/sample.py
pephubclient/modules/view.py
pephubclient/pephub_oauth/__init__.py
pephubclient/pephub_oauth/const.py
pephubclient/pephub_oauth/exceptions.py
pephubclient/pephub_oauth/models.py
pephubclient/pephub_oauth/pephub_oauth.py
pephubclient-0.4.3.dist-info/LICENSE.txt
pephubclient-0.4.3.dist-info/METADATA
pephubclient-0.4.3.dist-info/WHEEL
pephubclient-0.4.3.dist-info/entry_points.txt
pephubclient-0.4.3.dist-info/top_level.txt
pephubclient-0.4.3.dist-info/RECORD
