Metadata-Version: 2.1
Name: pephubclient
Version: 0.4.3
Summary: PEPhub command line interface.
Home-page: https://github.com/databio/pephubclient/
Author: Oleksandr Khoroshevskyi, Rafal Stepien
Author-email: khorosh@virginia.edu
License: BSD2
Keywords: project,bioinformatics,metadata
Classifier: Development Status :: 3 - Alpha
Classifier: License :: OSI Approved :: BSD License
Classifier: Programming Language :: Python :: 3.8
Classifier: Programming Language :: Python :: 3.9
Classifier: Programming Language :: Python :: 3.10
Classifier: Programming Language :: Python :: 3.11
Classifier: Programming Language :: Python :: 3.12
Classifier: Topic :: Scientific/Engineering :: Bio-Informatics
License-File: LICENSE.txt
Requires-Dist: typer >=0.7.0
Requires-Dist: peppy >=0.40.1
Requires-Dist: requests >=2.28.2
Requires-Dist: pydantic >2.5.0
Requires-Dist: pandas >=2.0.0
Requires-Dist: ubiquerg >=0.6.3
Requires-Dist: coloredlogs >=15.0.1
